sex_api/__init__.py
sex_api/api.py
sex_api/modules/__init__.py
sex_api/modules/consts.py
sex_api/modules/errors.py
sex_api/modules/searching_filters.py
sex_api/tests/__init__.py
sex_api/tests/test_board.py
sex_api/tests/test_pin.py
sex_api/tests/test_searching.py
sex_api/tests/test_user.py
sex_api-1.3.4.dist-info/licenses/LICENSE
sex_api-1.3.4.dist-info/METADATA
sex_api-1.3.4.dist-info/WHEEL
sex_api-1.3.4.dist-info/entry_points.txt
sex_api-1.3.4.dist-info/top_level.txt
sex_api-1.3.4.dist-info/RECORD
