Metadata-Version: 2.4
Name: Sex_API
Version: 1.3.4
Summary: A Python API for the Porn Site Sex.com/pins
Author-email: Johannes Habel <EchterAlsFake@proton.me>
License: GNU LESSER GENERAL PUBLIC LICENSE
Project-URL: Homepage, https://github.com/EchterAlsFake/Sex_API
Classifier: License :: OSI Approved :: GNU Lesser General Public License v3 (LGPLv3)
Classifier: Programming Language :: Python
License-File: LICENSE
Requires-Dist: eaf_base_api
Dynamic: license-file
